cmdz/__init__.py
cmdz/bus.py
cmdz/event.py
cmdz/handler.py
cmdz/object.py
cmdz/run.py
cmdz/thread.py
cmdz-4.data/data/cmdz/modz/cfg.py
cmdz-4.data/data/cmdz/modz/cmds.py
cmdz-4.data/data/cmdz/modz/dbg.py
cmdz-4.data/data/cmdz/modz/fnd.py
cmdz-4.data/data/cmdz/modz/inf.py
cmdz-4.data/data/cmdz/modz/irc.py
cmdz-4.data/data/cmdz/modz/log.py
cmdz-4.data/data/cmdz/modz/mbx.py
cmdz-4.data/data/cmdz/modz/rss.py
cmdz-4.data/data/cmdz/modz/shl.py
cmdz-4.data/data/cmdz/modz/tdo.py
cmdz-4.data/data/cmdz/modz/udp.py
cmdz-4.data/data/share/doc/cmdz/README.rst
cmdz-4.data/scripts/cmdz
cmdz-4.dist-info/METADATA
cmdz-4.dist-info/WHEEL
cmdz-4.dist-info/top_level.txt
cmdz-4.dist-info/RECORD
